Workbook

Sheet README
A1: HOW TO USE THIS WORKBOOK
A3: ► | B3: PURPOSE
B4: This workbook presents the Life Cycle Assessment (LCA) results for Carbon Nest, a 100 tCO₂/yr modular Direct Air Capture (DAC) facility in Kenya. It compares 6 energy and process scenarios to identify the configuration with the lowest carbon intensity per tonne of CO₂ captured.
A6: ► | B6: FUNCTIONAL UNIT
B7: All results are reported per 1 kg CO₂ captured at the plant gate (kgCO₂eq/kgCO₂). To convert to per-tonne: multiply by 1,000.
A9: ► | B9: WHAT THE NUMBERS MEAN
B10: A value of 0.65 kgCO₂eq/kgCO₂ means: for every 1 kg of CO₂ you pull from the atmosphere, you emit 0.65 kg of CO₂eq across the full supply chain. If this value is below 1.0, the facility is net-negative (removes more than it emits). If above 1.0, it is a net emitter.
A12: ► | B12: SHEET GUIDE
B13: • README — You are here. Start here. • Methodology — System boundary, database, impact method, key assumptions. • Input Parameters — All model inputs with units, sources, and categories. • Executive Summary — Headline results, scenario comparison, key findings. • Contribution Breakdown — What drives emissions in each scenario. • Sankey Diagrams — Activity Browser process flow diagrams (images). • Monte Carlo — Uncertainty analysis histograms and statistics. • Credit Issuance — Year-by-year carbon credit model under 3 accounting methods. • Benchmarking — Carbon Nest vs Climeworks Orca. • Improvement Pathway — Prioritized recommendations.
A15: ► | B15: COLOR CODING
B16: Blue text = editable input assumption. Black text = formula/calculated. Green highlight = net-negative. Red highlight = net-positive / warning. Yellow highlight = key result. Grey rows = alternating stripe for readability.
A18: ► | B18: UNITS
B19: kgCO₂eq/kgCO₂ = kilograms of CO₂-equivalent emitted per kilogram of CO₂ captured. tCO₂ = tonnes of CO₂. MWh = megawatt-hour. GWP100 = 100-year Global Warming Potential.
A21: ► | B21: CHARTS
B22: All charts in this workbook are dynamic Excel charts linked to the data tables. If you update values, charts update automatically.
A24: ► | B24: CONTACT
B25: For questions about this LCA, contact the MRV Associate

Sheet Methodology
A1: LCA METHODOLOGY & SYSTEM BOUNDARY
A2: Carbon Nest — 100 tCO₂/yr Modular DAC Facility, Kenya
B4: STUDY GOAL | C4: Quantify GHG emissions of DAC facility operation and infrastructure under different energy scenarios to determine the carbon intensity of CO₂ removal and support strategic decision-making.
B6: FUNCTIONAL UNIT | C6: 1 kg of CO₂ captured at the plant gate (liquid CO₂ after compression). All results in kgCO₂eq/kgCO₂ captured, using IPCC 2021 GWP100.
B8: SYSTEM BOUNDARY — CO₂ | C8: Cradle-to-gate. Includes all upstream emissions from energy, materials, sorbent, and solvent supply through to CO₂ liquefaction. Excludes downstream transport, storage, and utilization of captured CO₂.
B10: SYSTEM BOUNDARY — INFRASTRUCTURE | C10: Cradle-to-grave. Includes raw material extraction, manufacturing, international shipping (China → Mombasa), domestic transport (Mombasa → site), construction, 10-year operation, and end-of-life treatment.
B12: LCA SOFTWARE | C12: Activity Browser (Brightway2 front-end)
B14: BACKGROUND DATABASE | C14: ecoinvent 3.12, cut-off system model
B16: IMPACT METHOD | C16: IPCC 2021 — Climate Change — Global Warming Potential (GWP100)
B18: GEOGRAPHIC SCOPE | C18: Foreground: Kenya (KE). Background: ecoinvent Rest-of-World (RoW), Global (GLO), China (CN)
B20: ALLOCATION | C20: Cut-off (recycled content) approach per ecoinvent 3.12 system model.
B22: UNCERTAINTY | C22: Monte Carlo simulation (30 iterations) propagating ecoinvent parameter uncertainties. Results reported as mean, std dev, min, max, and % of runs achieving net-negative status.
B24: KEY EXCLUSIONS | C24: • CO₂ transport and storage/utilization (downstream) • Detailed solvent recovery unit CAPEX • Worker commuting and office operations • Water consumption impacts (single-impact study: GWP only)
B26: KEY PROXIES & LIMITATIONS | C26: • PEI sorbent modeled as high-density polyethylene (proxy) • Equipment modeled via mass-based industrial machine proxy • Transport distances based on standard shipping routes • Land carbon stock factors from IPCC literature values

Sheet Input Parameters
A1: CORE INPUT PARAMETERS
A2: Blue text = measured/editable values | All parameters used in Activity Browser model
A4: Parameter | B4: Value | C4: Unit | D4: Category | E4: Source | F4: Notes
A5: Plant capture capacity | B5: 100 | C5: tCO₂/year | D5: Operational | E5: Measured | F5: Design capacity
A6: Plant lifetime | B6: 10 | C6: years | D6: Operational | E6: Design | F6: Assumed for amortization
A7: Total lifetime capture | B7: 1000 | C7: tCO₂ | D7: Operational | E7: Calculated | F7: capacity *lifetime
A8: Electricity consumption | B8: 30 | C8: kWh/kgCO₂ | D8: Operational | E8: Measured | F8: Split: 27% direct, 73% boiler
A9: Direct electrical load share | B9: 0.27 | C9: fraction | D9: Operational | E9: Measured | F9: Fans, pumps, compressor
A10: Electric boiler share | B10: 0.73 | C10: fraction | D10: Operational | E10: Measured | F10: Steam generation (grid scenarios)
A11: Steam consumption | B11: 29 | C11: kg steam/kgCO₂ | D11: Operational | E11: Measured | F11: 4 bar saturated steam
A12: Steam enthalpy (4 bar) | B12: 2738 | C12: kJ/kg | D12: Physical | E12: Literature | F12: Saturated steam tables
A13: Boiler efficiency | B13: 0.98 | C13: fraction | D13: Operational | E13: Manufacturer | F13: Electric boiler
A14: Kenya grid EF (EPRA) | B14: 0.055 | C14: kgCO₂/kWh | D14: Energy | E14: EPRA Kenya | F14: National emission factor
A15: Geothermal elec EF | B15: ~0.004 | C15: kgCO₂/kWh | D15: Energy | E15: ecoinvent 3.12 | F15: Deep geothermal, KE
A16: Geothermal steam EF | B16: 0.0165 | C16: kgCO₂/MJ thermal | D16: Energy | E16: ecoinvent 3.12 | F16: Dissolved CO₂ + infrastructure
A17: PEI reload mass | B17: 22.29 | C17: kg/reload | D17: Sorbent | E17: Measured | F17: Per functionalization batch
A18: Functionalization interval | B18: 1.5 | C18: years | D18: Sorbent | E18: Measured | F18: Monolith re-coating cycle
A19: Methanol per batch | B19: 82.71 | C19: kg/batch | D19: Solvent | E19: Measured | F19: 89L × 0.792 kg/L density
A20: Methanol recovery rate | B20: 0 or 0.9 | C20: fraction | D20: Scenario | E20: Assumption | F20: 0 = base, 0.9 = optimized
A21: Steel (chromium 18/8) | B21: 25 | C21: kg/unit | D21: Embodied | E21: Design | F21: Hot rolled, RoW
A22: Shipping containers | B22: 0.004 | C22: units | D22: Embodied | E22: Design | F22: 40-ft intermodal, GLO
A23: Aluminium (primary) | B23: 0.06 | C23: kg/unit | D23: Embodied | E23: Design | F23: Ingot, IAI Africa
A24: Mild steel (low-alloyed) | B24: 5.5 | C24: kg/unit | D24: Embodied | E24: Design | F24: Electric, CH
A25: Equipment (industrial machine) | B25: 4.5 | C25: kg/unit | D25: Embodied | E25: Proxy | F25: Mass-based ecoinvent proxy
A26: Land area | B26: 2.5 | C26: acres | D26: Land Use | E26: Measured | F26: Site footprint
A27: Diesel (land clearing) | B27: 7.089 | C27: MJ | D27: Land Use | E27: Calculated | F27: Building machine fuel
A28: Total embodied emissions | B28: 221790 | C28: kgCO₂eq | D28: Embodied | E28: LCA result | F28: Over full facility lifetime
A29: Amortized embodied | B29: 221.79 | C29: kgCO₂eq/tCO₂ | D29: Embodied | E29: Calculated

Sheet Executive Summary
A1: SCENARIO COMPARISON — EXECUTIVE SUMMARY
A2: IPCC 2021 GWP100 | FU: 1 kgCO₂ captured at gate | Kenya | 100 tCO₂/yr | 10 yr lifetime
A4: HEADLINE RESULTS
A5: Scenario | B5: Total GWP100 (kgCO₂eq/kgCO₂) | C5: Threshold | D5: Net Removal Efficiency (%) | E5: Net Status | F5: Condition | G5: Reduction vs S1 (%) | H5: Electricity Source | I5: Steam Source
A6: S1: Grid + Boiler | B6: 4.8342 | C6: 1 | D6: =IF(B6<1,(1-B6)*100,0) -> 0 | E6: NET EMITTER ✗ | F6: Base | G6: =((B6-B6)/B6) -> 0 | H6: Kenya Grid | I6: Electric Boiler
A7: S2: Grid + Geo Steam | B7: 2.0912 | C7: 1 | D7: =IF(B7<1,(1-B7)*100,0) -> 0 | E7: NET EMITTER ✗ | F7: Base | G7: =((B6-B7)/B6)*100 -> 56.74155 | H7: Kenya Grid | I7: Geothermal
A8: S3: Geo Elec + Geo Steam | B8: 1.9383 | C8: 1 | D8: =IF(B8<1,(1-B8)*100,0) -> 0 | E8: NET EMITTER ✗ | F8: Base | G8: =((B6-B8)/B6)*100 -> 59.904431 | H8: Geothermal | I8: Geothermal
A9: S4: Opt Grid + Boiler | B9: 1.2264 | C9: 1 | D9: =IF(B9<1,(1-B9)*100,0) -> 0 | E9: NET EMITTER ✗ | F9: Optimized | G9: =((B6-B9)/B6)*100 -> 74.630756 | H9: Kenya Grid | I9: Electric Boiler
A10: S5: Opt Grid + Geo Steam | B10: 0.6589 | C10: 1 | D10: =IF(B10<1,(1-B10)*100,0) -> 34.11 | E10: NET NEGATIVE ✓ | F10: Optimized | G10: =((B6-B10)/B6)*100 -> 86.37003 | H10: Kenya Grid | I10: Geothermal
A11: S6: Opt Geo + Geo Steam | B11: 0.6518 | C11: 1 | D11: =IF(B11<1,(1-B11)*100,0) -> 34.82 | E11: NET NEGATIVE ✓ | F11: Optimized | G11: =((B6-B11)/B6)*100 -> 86.5169 | H11: Geothermal | I11: Geothermal
A32: Scenario | B32: Net Efficiency (%)
A33: S1 | B33: =D6 -> 0
A34: S2 | B34: =D7 -> 0
A35: S3 | B35: =D8 -> 0
A36: S4 | B36: =D9 -> 0
A37: S5 | B37: =D10 -> 34.11
A38: S6 | B38: =D11 -> 34.82
A58: KEY FINDINGS
A59: 1. Only S5 and S6 achieve net-negative carbon removal (total GWP < 1.0 kgCO₂eq/kgCO₂ captured).
A60: 2. Switching from electric boiler to geothermal steam reduces emissions by 47–48%.
A61: 3. Process optimization (reduced electricity and steam demand) cuts emissions by a further 56–66%.
A62: 4. Best scenario (S6) achieves 0.652 kgCO₂eq/kgCO₂ — meaning 35% net removal efficiency.
A63: 5. Steam supply is the dominant emission source (42–70% of total depending on scenario).
A64: 6. Embodied emissions (0.217 kgCO₂eq/kgCO₂) are fixed.

Sheet Contribution Breakdown
A1: FIRST-TIER CONTRIBUTION BREAKDOWN
A2: What drives emissions in each scenario? | Units: kgCO₂eq per kgCO₂ captured
A4: ABSOLUTE CONTRIBUTIONS (kgCO₂eq / kgCO₂)
A5: Component | B5: S1 | C5: S2 | D5: S3 | E5: S4 | F5: S5 | G5: S6
A6: Steam Supply | B6: 4.0532 | C6: 1.3101 | D6: 1.3101 | E6: 0.8386 | F6: 0.2711 | G6: 0.2711
A7: Electricity | B7: 0.41216 | C7: 0.4122 | D7: 0.2593 | E7: 0.018895 | F7: 0.018895 | G7: 0.011886
A8: Facility Embodied | B8: 0.2167 | C8: 0.2167 | D8: 0.2167 | E8: 0.2167 | F8: 0.2167 | G8: 0.2167
A9: Methanol | B9: 0.0834 | C9: 0.0834 | D9: 0.0834 | E9: 0.0834 | F9: 0.0834 | G9: 0.0834
A10: PEI Sorbent | B10: 0.0688 | C10: 0.0688 | D10: 0.0688 | E10: 0.0688 | F10: 0.0688 | G10: 0.0688
A11: TOTAL | B11: =SUM(B6:B10) -> 4.83426 | C11: =SUM(C6:C10) -> 2.0912 | D11: =SUM(D6:D10) -> 1.9383 | E11: =SUM(E6:E10) -> 1.226395 | F11: =SUM(F6:F10) -> 0.658895 | G11: =SUM(G6:G10) -> 0.651886
A33: RELATIVE SHARE (%)
A34: Component | B34: S1 | C34: S2 | D34: S3 | E34: S4 | F34: S5 | G34: S6
A35: Steam Supply | B35: 70.2 | C35: 43.3 | D35: 67.6 | E35: 66.1 | F35: 38.6 | G35: 41.6
A36: Electricity | B36: 23.4 | C36: 44.6 | D36: 13.4 | E36: 4.9 | F36: 8.8 | G36: 1.8
A37: Facility Embodied | B37: 3.8 | C37: 7.2 | D37: 11.2 | E37: 17.1 | F37: 30.9 | G37: 33.2
A38: Methanol | B38: 1.4 | C38: 2.8 | D38: 4.3 | E38: 6.6 | F38: 11.9 | G38: 12.8
A39: PEI Sorbent | B39: 1.2 | C39: 2.3 | D39: 3.5 | E39: 5.4 | F39: 9.8 | G39: 10.6
A42: S6 Component | B42: kgCO₂eq/kgCO₂
A43: Steam Supply | B43: 0.2711
A44: Electricity | B44: 0.0119
A45: Embodied | B45: 0.2167
A46: Methanol | B46: 0.0834
A47: PEI | B47: 0.0688
A67: HOW TO READ THIS
A68: • Steam Supply = emissions from generating 29 kg steam per kgCO₂ (electric boiler or geothermal well).
A69: • Electricity = emissions from 30 kWh/kgCO₂ electrical demand (Kenya grid or geothermal).
A70: • Facility Embodied = amortized construction emissions (steel, containers, equipment) over 10yr/1000t lifetime.
A71: • Methanol = upstream emissions from producing methanol used as wash solvent (82.71 kg/batch).
A72: • PEI Sorbent = upstream emissions from manufacturing PEI reload material (22.29 kg every 1.5 yr).
A73: • Key insight: when fossil energy is removed, embodied + consumables become the dominant contributors.

Sheet Sankey Diagrams
A1: PROCESS FLOW SANKEY DIAGRAMS (from Activity Browser)
A2: These diagrams show the contribution of each upstream process to the total GWP. Line thickness and percentage labels indicate relative contribution. Generated in Activity Browser.
A4: S1: Grid Elec + Boiler Steam
A44: S2: Grid Elec + Geothermal Steam
A84: S3: Geothermal Elec + Geothermal Steam
A124: S4: Optimized Grid + Boiler
A164: S5: Optimized Grid + Geothermal Steam
A204: S6: Optimized Geo + Geo Steam

Sheet Monte Carlo Uncertainty
A1: MONTE CARLO UNCERTAINTY ANALYSIS
A2: 30 iterations per scenario | Propagates ecoinvent parameter distributions | IPCC 2021 GWP100
A4: WHAT THIS SHOWS: Each scenario was run 30 times with randomly sampled parameter values from ecoinvent uncertainty distributions.
A5: WHY IT MATTERS: The deterministic result is a single "best estimate." Monte Carlo shows the range of plausible outcomes and your confidence in net-negative claims.
A6: HOW TO READ: If most runs fall below 1.0, you can claim net-negative with high confidence. Wide spread = sensitive to background data assumptions.
A8: SUMMARY STATISTICS
A9: Scenario | B9: Deterministic (kgCO₂eq/kgCO₂) | C9: MC Mean | D9: MC Std Dev | E9: MC Min | F9: MC Max | G9: % Runs < 1.0 (Net Negative)
A10: S1: Grid + Boiler | B10: ='Contribution Breakdown'!B11 -> 4.83426 | C10: =AVERAGE(B19:B48) -> 5.6872614 | D10: =STDEV(B19:B48) -> 8.3075297 | E10: =MIN(B19:B48) -> -13.630662 | F10: =MAX(B19:B48) -> 29.198491 | G10: =COUNTIF(B19:B48,"<1")/COUNT(B19:B48) -> 0.3
A11: S2: Grid + Geothermal | B11: ='Contribution Breakdown'!C11 -> 2.0912 | C11: =AVERAGE(C19:C48) -> 2.1301323 | D11: =STDEV(C19:C48) -> 0.18334922 | E11: =MIN(C19:C48) -> 1.7469193 | F11: =MAX(C19:C48) -> 2.5255435 | G11: =COUNTIF(C19:C48,"<1")/COUNT(C19:C48) -> 0
A12: S3: Geo Elec + Geo Steam | B12: ='Contribution Breakdown'!D11 -> 1.9383 | C12: =AVERAGE(D19:D48) -> 2.2749764 | D12: =STDEV(D19:D48) -> 1.3970719 | E12: =MIN(D19:D48) -> 0.85012113 | F12: =MAX(D19:D48) -> 9.1513841 | G12: =COUNTIF(D19:D48,"<1")/COUNT(D19:D48) -> 0.033333333
A13: S4: Opt Grid + Boiler | B13: ='Contribution Breakdown'!E11 -> 1.226395 | C13: =AVERAGE(E19:E48) -> 1.4191833 | D13: =STDEV(E19:E48) -> 1.2278209 | E13: =MIN(E19:E48) -> -0.83195408 | F13: =MAX(E19:E48) -> 4.4262121 | G13: =COUNTIF(E19:E48,"<1")/COUNT(E19:E48) -> 0.36666667
A14: S5: Opt Grid + Geo Steam | B14: ='Contribution Breakdown'!F11 -> 0.658895 | C14: =AVERAGE(F19:F48) -> 0.66514433 | D14: =STDEV(F19:F48) -> 0.24180229 | E14: =MIN(F19:F48) -> -0.056024725 | F14: =MAX(F19:F48) -> 1.3383704 | G14: =COUNTIF(F19:F48,"<1")/COUNT(F19:F48) -> 0.93333333
A15: S6: Opt Geo + Geo Steam | B15: ='Contribution Breakdown'!G11 -> 0.651886 | C15: =AVERAGE(G19:G48) -> 0.68473093 | D15: =STDEV(G19:G48) -> 0.14685135 | E15: =MIN(G19:G48) -> 0.29124366 | F15: =MAX(G19:G48) -> 0.96058298 | G15: =COUNTIF(G19:G48,"<1")/COUNT(G19:G48) -> 1
A18: Run # | B18: S1 | C18: S2 | D18: S3 | E18: S4 | F18: S5 | G18: S6
A19: 1 | B19: -0.16187716 | C19: 1.9746343 | D19: 2.4849148 | E19: 1.5350297 | F19: 0.91284917 | G19: 0.82932604
A20: 2 | B20: 0.41764815 | C20: 2.2448947 | D20: 2.1255555 | E20: -0.041541816 | F20: 0.68958793 | G20: 0.96058298
A21: 3 | B21: 15.958725 | C21: 2.0440277 | D21: 2.4141649 | E21: 2.0779595 | F21: 0.41456495 | G21: 0.72582378
A22: 4 | B22: 15.721709 | C22: 2.211222 | D22: 2.791502 | E22: 0.57070111 | F22: 0.61460203 | G22: 0.52749109
A23: 5 | B23: -13.630662 | C23: 2.106116 | D23: 1.9269894 | E23: 1.9952337 | F23: -0.056024725 | G23: 0.54501458
A24: 6 | B24: -0.61318502 | C24: 1.7929456 | D24: 2.6531382 | E24: 1.5341924 | F24: 0.62385664 | G24: 0.71480969
A25: 7 | B25: 3.6259059 | C25: 2.1233177 | D25: 1.217211 | E25: 0.074180994 | F25: 0.57553226 | G25: 0.81183234
A26: 8 | B26: 5.2580857 | C26: 2.1452845 | D26: 1.7109239 | E26: 1.1065842 | F26: 0.75140044 | G26: 0.72291811
A27: 9 | B27: 6.79531 | C27: 2.2211894 | D27: 1.6665637 | E27: 2.9348666 | F27: 0.86570053 | G27: 0.62217803
A28: 10 | B28: 8.1961423 | C28: 2.2796469 | D28: 1.9252711 | E28: 1.5843182 | F28: 0.87145609 | G28: 0.80384451
A29: 11 | B29: 16.02942 | C29: 2.0224085 | D29: 0.85012113 | E29: 0.23704306 | F29: 0.51246597 | G29: 0.44576457
A30: 12 | B30: -2.9093084 | C30: 2.4417439 | D30: 2.0580192 | E30: 2.0038791 | F30: 0.59679627 | G30: 0.61601984
... A48: 30 | B48: 11.413072 | C48: 1.8259605 | D48: 2.0480033 | E48: 2.3413208 | F48: 0.63256136 | G48: 0.65679013
A52: ACTIVITY BROWSER HISTOGRAMS (original outputs):
A54: S1 Histogram
A71: S2 Histogram
A88: S3 Histogram
A105: S4 Histogram
A122: S5 Histogram
A140: S6 Histogram
A156: INTERPRETATION
A157: 1. S1 has extreme variance (σ=8.308) — the fossil fuel supply chain introduces massive uncertainty.
A158: 2. S6 is the most stable (σ=0.15) — geothermal energy has narrow uncertainty bands in ecoinvent.
A159: 3. MC mean for S6 (0.68) > deterministic (0.65) — use MC mean for conservative carbon accounting.
A160: 4. The "% < 1.0" column is your confidence level for net-negative claims.
A161: 5. LIMITATION: 30 iterations is low.

Sheet Credit Issuance
A1: CARBON CREDIT ISSUANCE MODEL
A2: Scenario S6 (Opt Geo+Geo, 0.652 kgCO₂eq/kgCO₂) |
A4: THE PROBLEM: Your facility emits 221.79 tCO₂eq during construction before capturing anything. This "carbon debt" must be accounted for before issuing carbon removal credits. Two methods exist, each with different credibility implications.
A6: ASSUMPTIONS (S6)
A7: Annual gross capture | B7: 100 tCO₂/yr
A8: Annual operational emissions | B8: 43.5 tCO₂eq/yr
A9: Annual net removal (before embodied) | B9: 56.5 tCO₂/yr
A10: Total embodied emissions | B10: 221.79 tCO₂eq
A11: Embodied payback period | B11: 3.93 years
A13: YEAR-BY-YEAR COMPARISON (tCO₂)
A14: Method / Year | B14: Yr 0 (Build) | C14: Yr 1 | D14: Yr 2 | E14: Yr 3 | F14: Yr 4 | G14: Yr 5 | H14: Yr 6 | I14: Yr 7 | J14: Yr 8 | K14: Yr 9 | L14: Yr 10
A15: A: AMORTIZE credits/yr | B15: 0 | C15: 34.32 | D15: 34.32 | E15: 34.32 | F15: 34.32 | G15: 34.32 | H15: 34.32 | I15: 34.32 | J15: 34.32 | K15: 34.32 | L15: 34.32
A16: A: Cumulative credits | B16: 0 | C16: 34.3 | D16: 68.6 | E16: 103 | F16: 137.3 | G16: 171.6 | H16: 205.9 | I16: 240.2 | J16: 274.6 | K16: 308.9 | L16: 343.2
A18: B: PAYBACK FIRST credits/yr | B18: 0 | C18: 0 | D18: 0 | E18: 0 | F18: 4.21 | G18: 56.5 | H18: 56.5 | I18: 56.5 | J18: 56.5 | K18: 56.5 | L18: 56.5
A19: B: Cumulative credits | B19: 0 | C19: 0 | D19: 0 | E19: 0 | F19: 4.2 | G19: 60.7 | H19: 117.2 | I19: 173.7 | J19: 230.2 | K19: 286.7 | L19: 343.2
A41: METHOD EXPLANATIONS
A42: A: AMORTIZE (Climeworks method)
A43: Spread 221.79 tCO₂eq evenly over 10 years (22.18 t/yr deduction). Issue credits from year 1. Simple and immediate revenue, BUT: Calyx Global downgraded Climeworks to Tier 3 (lowest) partly because of this approach. Risk: if plant shuts down early, issued credits exceed actual net removal.
A45: B: PAYBACK FIRST (Calyx/Meta recommended)
A46: Issue zero credits until cumulative net removal equals embodied debt (221.79 t). First credits in year 4. Zero revenue for ~4 years, BUT: guarantees atmosphere has genuinely benefited at every point. Highest market credibility. Recommended for new projects.

Sheet Benchmarking
A1: BENCHMARKING — CARBON NEST vs CLIMEWORKS ORCA
A4: Metric | B4: Carbon Nest Best (S6) | C4: Carbon Nest Mid (S5) | D4: Climeworks Orca Actual (2023) | E4: Climeworks Orca Design Target
A5: Total grey emissions (kgCO₂eq/kgCO₂) | B5: 0.652 | C5: 0.702 | D5: 0.20 – 0.25 | E5: < 0.10
A6: Net removal efficiency | B6: =(1-B5) -> 0.348 | C6: =(1-C5) -> 0.298 | D6: 75 – 80% | E6: > 90%
A7: Embodied emissions (kgCO₂eq/kgCO₂) | B7: 0.217 | C7: 0.217 | D7: ~0.015 | E7: < 0.015
A8: Embodied as % of total | B8: =(B7/B5) -> 0.33282209 | C8: =C7/C5 -> 0.30911681 | D8: ~6 – 8% | E8: < 10%
A9: Annual capture capacity (tCO₂/yr) | B9: 100 | C9: 100 | D9: 4,000 (design) | E9: 4,000+
A10: Energy source | B10: Geothermal | C10: Grid + Geothermal | D10: Geothermal (Iceland) | E10: Low-carbon required
A11: Embodied payback period | B11: Amortized over 10 years | C11: Amortized over 10 years | D11: Amortized over 12 yr | E11: Upfront deduction
A12: Calyx Global rating risk | D12: Tier 3 (lowest) | E12: Target: Tier 1
A13: BeZero Carbon rating | B13: N/A | C13: N/A | D13: AAA (highest) | E13: N/A
A16: KEY GAPS TO CLOSE
A17: 1. The embodied emissions (0.217) are ~14x higher than Climeworks (~0.015). Primary driver: scale (100 t vs 4,000 t).
A18: 2. The net removal efficiency (35%) is roughly half of Orca actual (75-80%).
A19: 3. Scaling to 1,000+ t/yr is the single most impactful move to close the embodied emissions gap.
